_foo.cpython-310-x86_64-linux-gnu.so
deepray/__init__.py
deepray/conftest.py
deepray/design_patterns.py
deepray/options.py
deepray/register.py
deepray/version.py
deepray/activations/__init__.py
deepray/activations/hardshrink.py
deepray/activations/lisht.py
deepray/activations/mish.py
deepray/activations/rrelu.py
deepray/activations/snake.py
deepray/activations/softshrink.py
deepray/activations/sparsemax.py
deepray/activations/swish.py
deepray/activations/tanhshrink.py
deepray/callbacks/__init__.py
deepray/callbacks/average_model_checkpoint.py
deepray/callbacks/callbacks.py
deepray/callbacks/model_checkpoint.py
deepray/callbacks/profiler_callback.py
deepray/callbacks/progbar_logger.py
deepray/callbacks/time_history.py
deepray/callbacks/time_stopping.py
deepray/callbacks/tqdm_progress_bar.py
deepray/callbacks/training_speed.py
deepray/core/__init__.py
deepray/core/compile_utils.py
deepray/core/export_saved_model.py
deepray/core/modeling_tf_utils.py
deepray/core/runner.py
deepray/core/standard_runner.py
deepray/core/trainer.py
deepray/core/common/__init__.py
deepray/core/common/distribution_utils.py
deepray/core/common/flags.py
deepray/core/common/registry_imports.py
deepray/core/common/streamz_counters.py
deepray/core/utils/__init__.py
deepray/core/utils/clip.py
deepray/core/utils/common.py
deepray/core/utils/epoch_helper.py
deepray/core/utils/loop_fns.py
deepray/core/utils/summary_manager.py
deepray/core/utils/summary_manager_interface.py
deepray/core/utils/tpu_summaries.py
deepray/core/utils/misc/__init__.py
deepray/core/utils/misc/callstack_sampler.py
deepray/core/utils/misc/distribution_utils.py
deepray/core/utils/misc/model_helpers.py
deepray/core/utils/misc/tpu_lib.py
deepray/custom_ops/__init__.py
deepray/custom_ops/correlation_cost/__init__.py
deepray/custom_ops/correlation_cost/_correlation_cost_ops.so
deepray/custom_ops/correlation_cost/python/__init__.py
deepray-0.21.97.dist-info/LICENSE
deepray-0.21.97.dist-info/METADATA
deepray-0.21.97.dist-info/WHEEL
deepray-0.21.97.dist-info/top_level.txt
deepray-0.21.97.dist-info/RECORD
