Metadata-Version: 2.1
Name: deepray
Version: 0.21.97
Summary: Deepray.
Author: Hailin Fu
Author-email: hailinfufu@outlook.com
License: Apache 2.0
Keywords: tensorflow deepray machine learning
Classifier: Development Status :: 4 - Beta
Classifier: Intended Audience :: Developers
Classifier: Intended Audience :: Education
Classifier: Intended Audience :: Science/Research
Classifier: License :: OSI Approved :: Apache Software License
Classifier: Programming Language :: Python :: 3
Classifier: Programming Language :: Python :: 3.10
Classifier: Topic :: Scientific/Engineering :: Mathematics
Classifier: Topic :: Software Development :: Libraries :: Python Modules
Classifier: Topic :: Software Development :: Libraries
License-File: LICENSE
Requires-Dist: tabulate
Requires-Dist: fastavro
Requires-Dist: boto3
Requires-Dist: pandas
Requires-Dist: scikit-build
Requires-Dist: scikit-learn
Requires-Dist: typeguard
Requires-Dist: tqdm
Requires-Dist: keras ==2.15.0
Requires-Dist: tf-keras ==2.15.1
Requires-Dist: nvidia-ml-py
Provides-Extra: tensorflow
Requires-Dist: tensorflow <2.18.0,>=2.9.1 ; extra == 'tensorflow'
